README.rst
setup.py
scrapydo/__init__.py
scrapydo/api.py
scrapydo/tests.py
scrapydo/utils.py
scrapydo.egg-info/PKG-INFO
scrapydo.egg-info/SOURCES.txt
scrapydo.egg-info/dependency_links.txt
scrapydo.egg-info/requires.txt
scrapydo.egg-info/top_level.txt