Metadata-Version: 1.1
Name: scrapydo
Version: 0.1.0
Summary: Crochet-based blocking API for Scrapy.
Home-page: https://github.com/darkrho/scrapydo
Author: Rolando Espinoza La fuente
Author-email: darkrho@gmail.com
License: MIT
Platform: UNKNOWN
Classifier: Programming Language :: Python
Classifier: Development Status :: 4 - Beta
Classifier: Intended Audience :: Developers
